<?xml version="1.0" encoding="UTF-8"?>
<inforef>
  <fileref>
    <file>
      <id>244649</id>
    </file>
    <file>
      <id>244650</id>
    </file>
    <file>
      <id>244651</id>
    </file>
    <file>
      <id>244652</id>
    </file>
    <file>
      <id>244653</id>
    </file>
    <file>
      <id>247378</id>
    </file>
    <file>
      <id>247379</id>
    </file>
    <file>
      <id>247380</id>
    </file>
    <file>
      <id>247381</id>
    </file>
    <file>
      <id>247382</id>
    </file>
    <file>
      <id>247383</id>
    </file>
    <file>
      <id>247384</id>
    </file>
    <file>
      <id>247385</id>
    </file>
    <file>
      <id>247386</id>
    </file>
    <file>
      <id>247387</id>
    </file>
    <file>
      <id>247388</id>
    </file>
    <file>
      <id>247389</id>
    </file>
    <file>
      <id>247390</id>
    </file>
    <file>
      <id>247391</id>
    </file>
    <file>
      <id>247392</id>
    </file>
    <file>
      <id>247393</id>
    </file>
    <file>
      <id>247394</id>
    </file>
    <file>
      <id>247395</id>
    </file>
    <file>
      <id>247396</id>
    </file>
    <file>
      <id>247397</id>
    </file>
    <file>
      <id>247398</id>
    </file>
    <file>
      <id>247399</id>
    </file>
    <file>
      <id>247400</id>
    </file>
    <file>
      <id>247401</id>
    </file>
    <file>
      <id>247402</id>
    </file>
    <file>
      <id>247403</id>
    </file>
    <file>
      <id>247404</id>
    </file>
    <file>
      <id>247405</id>
    </file>
    <file>
      <id>247406</id>
    </file>
  </fileref>
</inforef>